tdd_guard_pytest/__init__.py
tdd_guard_pytest/pytest_reporter.py
tdd_guard_pytest-0.1.2.dist-info/METADATA
tdd_guard_pytest-0.1.2.dist-info/WHEEL
tdd_guard_pytest-0.1.2.dist-info/entry_points.txt
tdd_guard_pytest-0.1.2.dist-info/top_level.txt
tdd_guard_pytest-0.1.2.dist-info/RECORD
