Metadata-Version: 2.4
Name: tdd-guard-pytest
Version: 0.1.2
Summary: Pytest plugin for TDD Guard - enforces Test-Driven Development principles
Author: Nizar Selander, Durafen
License-Expression: MIT
Project-URL: Homepage, https://github.com/nizos/tdd-guard
Project-URL: Repository, https://github.com/nizos/tdd-guard
Project-URL: Bug Tracker, https://github.com/nizos/tdd-guard/issues
Project-URL: Documentation, https://github.com/nizos/tdd-guard/tree/main/reporters/pytest
Keywords: tdd,test-driven-development,testing,pytest,claude
Classifier: Development Status :: 4 - Beta
Classifier: Framework :: Pytest
Classifier: Intended Audience :: Developers
Classifier: Programming Language :: Python :: 3
Classifier: Programming Language :: Python :: 3.8
Classifier: Programming Language :: Python :: 3.9
Classifier: Programming Language :: Python :: 3.10
Classifier: Programming Language :: Python :: 3.11
Classifier: Programming Language :: Python :: 3.12
Classifier: Programming Language :: Python :: 3.13
Classifier: Topic :: Software Development :: Testing
Classifier: Topic :: Software Development :: Quality Assurance
Requires-Python: >=3.8
Requires-Dist: pytest>=6.0
